memo_ms/__init__.py
memo_ms/__version__.py
memo_ms/classes.py
memo_ms/import_data.py
memo_ms/visualization.py
memo_ms-0.1.4.dist-info/LICENSE
memo_ms-0.1.4.dist-info/METADATA
memo_ms-0.1.4.dist-info/WHEEL
memo_ms-0.1.4.dist-info/top_level.txt
memo_ms-0.1.4.dist-info/RECORD
