Metadata-Version: 2.1
Name: memo-ms
Version: 0.1.4
Summary: Python package to perform MS2 Based Sample Vectorization and visualization
Home-page: https://github.com/mandelbrot-project/memo
Author: Arnaud Gaudry
Author-email: arnaud.gaudry@unige.ch
License: UNKNOWN
Platform: UNKNOWN
Classifier: Programming Language :: Python :: 3
Classifier: License :: OSI Approved :: MIT License
Classifier: Operating System :: OS Independent
Requires-Python: >=3.7
Requires-Dist: ipykernel
Requires-Dist: pandas
Requires-Dist: numpy
Requires-Dist: jupyter (>=1.0.0)
Requires-Dist: matchms (>=0.9.0)
Requires-Dist: spec2vec (>=0.4)
Requires-Dist: plotly (>=4.14.3)
Requires-Dist: cimcb-lite (>=1.0.2)
Requires-Dist: scikit-bio (>=0.5.6)
Requires-Dist: scikit-learn (>=0.24.1)
Provides-Extra: dev
Requires-Dist: isort (<5,>=4.2.5) ; extra == 'dev'
Requires-Dist: prospector[with_pyroma] ; extra == 'dev'
Requires-Dist: pytest ; extra == 'dev'
Requires-Dist: pytest-cov ; extra == 'dev'
Requires-Dist: sphinx (!=3.2.0,!=3.5.0,<4.0.0,>=3.0.0) ; extra == 'dev'
Requires-Dist: sphinx-rtd-theme ; extra == 'dev'
Requires-Dist: sphinxcontrib-apidoc ; extra == 'dev'
